auto_flutter_dig/__init__.py
auto_flutter_dig/__main__.py
auto_flutter_dig/main.py
auto_flutter_dig/core/__init__.py
auto_flutter_dig/core/config.py
auto_flutter_dig/core/logger.py
auto_flutter_dig/core/version.py
auto_flutter_dig/core/json/__init__.py
auto_flutter_dig/core/json/codec.py
auto_flutter_dig/core/json/decode.py
auto_flutter_dig/core/json/encode.py
auto_flutter_dig/core/json/serializable.py
auto_flutter_dig/core/json/type.py
auto_flutter_dig/core/os/__init__.py
auto_flutter_dig/core/os/executable_resolver.py
auto_flutter_dig/core/os/os.py
auto_flutter_dig/core/os/path_converter.py
auto_flutter_dig/core/process/__init__.py
auto_flutter_dig/core/process/process.py
auto_flutter_dig/core/process/subprocess.py
auto_flutter_dig/core/string/__init__.py
auto_flutter_dig/core/string/builder.py
auto_flutter_dig/core/string/formatter.py
auto_flutter_dig/core/task/__init__.py
auto_flutter_dig/core/task/_unique_identity.py
auto_flutter_dig/core/task/manager.py
auto_flutter_dig/core/task/resolver.py
auto_flutter_dig/core/task/watcher.py
auto_flutter_dig/core/task/printer/__init__.py
auto_flutter_dig/core/task/printer/operation.py
auto_flutter_dig/core/task/printer/printer.py
auto_flutter_dig/core/utils/__init__.py
auto_flutter_dig/core/utils/dict.py
auto_flutter_dig/core/utils/ensure.py
auto_flutter_dig/core/utils/enum.py
auto_flutter_dig/core/utils/if_.py
auto_flutter_dig/core/utils/iterable.py
auto_flutter_dig/core/utils/lazy.py
auto_flutter_dig/core/utils/raise_.py
auto_flutter_dig/core/utils/task/__init__.py
auto_flutter_dig/core/utils/task/subtask_parent_task.py
auto_flutter_dig/core/utils/task/subtask_run_all.py
auto_flutter_dig/core/utils/task/process/__init__.py
auto_flutter_dig/core/utils/task/process/check.py
auto_flutter_dig/core/utils/task/process/interval.py
auto_flutter_dig/core/utils/task/process/process.py
auto_flutter_dig/core/utils/task/process/timeout.py
auto_flutter_dig/model/__init__.py
auto_flutter_dig/model/result.py
auto_flutter_dig-0.6.2.dist-info/METADATA
auto_flutter_dig-0.6.2.dist-info/WHEEL
auto_flutter_dig-0.6.2.dist-info/entry_points.txt
auto_flutter_dig-0.6.2.dist-info/license.txt
auto_flutter_dig-0.6.2.dist-info/top_level.txt
auto_flutter_dig-0.6.2.dist-info/RECORD
